csvorm/__init__.py
csvorm/compat.py
csvorm/version.txt
csvorm/tests/__init__.py
csvorm/tests/test_it.py
csvorm-0.1.5.dist-info/DESCRIPTION.rst
csvorm-0.1.5.dist-info/entry_points.txt
csvorm-0.1.5.dist-info/METADATA
csvorm-0.1.5.dist-info/metadata.json
csvorm-0.1.5.dist-info/namespace_packages.txt
csvorm-0.1.5.dist-info/RECORD
csvorm-0.1.5.dist-info/top_level.txt
csvorm-0.1.5.dist-info/WHEEL
