Metadata-Version: 2.0
Name: csvorm
Version: 0.1.5
Summary: orm for csv
Home-page: https://github.com/TakesxiSximada/csvorm
Author: TakesxiSximada
Author-email: takesxi.sximada@gmail.com
License: See http://www.python.org/3.4/license.html
Download-URL: https://github.com/TakesxiSximada/csvorm
Keywords: csv
Platform: any
Classifier: Development Status :: 4 - Beta
Classifier: Intended Audience :: Developers
Classifier: Intended Audience :: Information Technology
Classifier: Intended Audience :: System Administrators
Classifier: Natural Language :: English
Classifier: Operating System :: MacOS :: MacOS X
Classifier: Operating System :: Microsoft :: Windows
Classifier: Operating System :: POSIX
Classifier: Programming Language :: Python :: 2
Classifier: Programming Language :: Python :: 2.7
Classifier: Programming Language :: Python :: 3
Classifier: Programming Language :: Python :: 3.4
Requires-Dist: six
Requires-Dist: unicodecsv
Requires-Dist: nose
Requires-Dist: tox
